[{"header":{"msg_type":"0003","source_dev_id":"","user_id":"","original_data_source":"SMART","msg_queue_timestamp":"1484748848000","source_system_id":"TRUST"},"body":{"event_type":"DEPARTURE","gbtt_timestamp":"1484748840000","original_loc_stanox":"","planned_timestamp":"1484748840000","timetable_variation":"1","original_loc_timestamp":"","current_train_id":"","delay_monitoring_point":"true","next_report_run_time":"5","reporting_stanox":"86087","actual_timestamp":"1484748780000","correction_ind":"false","event_source":"AUTOMATIC","train_file_address":null,"platform":" 1","division_code":"84","train_terminated":"false","train_id":"862B48ML18","offroute_ind":"false","variation_status":"EARLY","train_service_code":"24620204","toc_id":"84","loc_stanox":"86087","auto_expected":"true","direction_ind":"UP","route":"2","planned_event_type":"DEPARTURE","next_report_stanox":"86084","line_ind":"F"}},{"header":{"msg_type":"0003","source_dev_id":"","user_id":"","original_data_source":"SMART","msg_queue_timestamp":"1484748848000","source_system_id":"TRUST"},"body":{"event_type":"ARRIVAL","gbtt_timestamp":"1484748540000","original_loc_stanox":"","planned_timestamp":"1484748540000","timetable_variation":"5","original_loc_timestamp":"","current_train_id":"","delay_monitoring_point":"false","next_report_run_time":"1","reporting_stanox":"00000","actual_timestamp":"1484748840000","correction_ind":"false","event_source":"AUTOMATIC","train_file_address":null,"platform":" 2","division_code":"80","train_terminated":"false","train_id":"882R38MM18","offroute_ind":"false","variation_status":"LATE","train_service_code":"24605004","toc_id":"80","loc_stanox":"89326","auto_expected":"true","direction_ind":"DOWN","route":"0","planned_event_type":"ARRIVAL","next_report_stanox":"89323","line_ind":""}},{"header":{"msg_type":"0003","source_dev_id":"","user_id":"","original_data_source":"SMART","msg_queue_timestamp":"1484748848000","source_system_id":"TRUST"},"body":{"event_type":"ARRIVAL","gbtt_timestamp":"1484748900000","original_loc_stanox":"","planned_timestamp":"1484748870000","timetable_variation":"0","original_loc_timestamp":"","current_train_id":"","delay_monitoring_point":"true","next_report_run_time":"1","reporting_stanox":"43031","actual_timestamp":"1484748840000","correction_ind":"false","event_source":"AUTOMATIC","train_file_address":null,"platform":" 3","division_code":"29","train_terminated":"false","train_id":"421U34MO18","offroute_ind":"false","variation_status":"ON TIME","train_service_code":"22330000","toc_id":"29","loc_stanox":"43031","auto_expected":"true","direction_ind":"UP","route":"0","planned_event_type":"ARRIVAL","next_report_stanox":"43211","line_ind":""}},{"header":{"msg_type":"0003","source_dev_id":"","user_id":"","original_data_source":"SMART","msg_queue_timestamp":"1484748848000","source_system_id":"TRUST"},"body":{"event_type":"DEPARTURE","gbtt_timestamp":"","original_loc_stanox":"","planned_timestamp":"1484748900000","timetable_variation":"1","original_loc_timestamp":"","current_train_id":"","delay_monitoring_point":"true","next_report_run_time":"3","reporting_stanox":"32515","actual_timestamp":"1484748840000","correction_ind":"false","event_source":"AUTOMATIC","train_file_address":null,"platform":"","division_code":"65","train_terminated":"false","train_id":"325A24MO18","offroute_ind":"false","variation_status":"EARLY","train_service_code":"22112002","toc_id":"65","loc_stanox":"32515","auto_expected":"true","direction_ind":"UP","route":"2","planned_event_type":"DEPARTURE","next_report_stanox":"32525","line_ind":"S"}},{"header":{"msg_type":"0003","source_dev_id":"","user_id":"","original_data_source":"SMART","msg_queue_timestamp":"1484748848000","source_system_id":"TRUST"},"body":{"event_type":"DEPARTURE","gbtt_timestamp":"1484748840000","original_loc_stanox":"","planned_timestamp":"1484748870000","timetable_variation":"1","original_loc_timestamp":"","current_train_id":"","delay_monitoring_point":"false","next_report_run_time":"3","reporting_stanox":"00000","actual_timestamp":"1484748780000","correction_ind":"false","event_source":"AUTOMATIC","train_file_address":null,"platform":"","division_code":"64","train_terminated":"false","train_id":"362O32MO18","offroute_ind":"false","variation_status":"EARLY","train_service_code":"12304212","toc_id":"64","loc_stanox":"36078","auto_expected":"true","direction_ind":"DOWN","route":"2","planned_event_type":"DEPARTURE","next_report_stanox":"36076","line_ind":""}},{"header":{"msg_type":"0003","source_dev_id":"","user_id":"","original_data_source":"SMART","msg_queue_timestamp":"1484748848000","source_system_id":"TRUST"},"body":{"event_type":"DEPARTURE","gbtt_timestamp":"","original_loc_stanox":"","planned_timestamp":"1484749110000","timetable_variation":"4","original_loc_timestamp":"","current_train_id":null,"delay_monitoring_point":"true","next_report_run_time":"2","reporting_stanox":"35591","actual_timestamp":"1484748840000","correction_ind":"false","event_source":"AUTOMATIC","train_file_address":"ATL","platform":"","division_code":"00","train_terminated":"false","train_id":"35628HCO18","offroute_ind":"false","variation_status":"EARLY","train_service_code":"52406842","toc_id":"00","loc_stanox":"35591","auto_expected":"true","direction_ind":"UP","route":"3","planned_event_type":"DEPARTURE","next_report_stanox":"37001","line_ind":"M"}},{"header":{"msg_type":"0003","source_dev_id":"","user_id":"","original_data_source":"SMART","msg_queue_timestamp":"1484748848000","source_system_id":"TRUST"},"body":{"event_type":"ARRIVAL","gbtt_timestamp":"1484748780000","original_loc_stanox":"","planned_timestamp":"1484748750000","timetable_variation":"2","original_loc_timestamp":"","current_train_id":"","delay_monitoring_point":"true","next_report_run_time":"1","reporting_stanox":"04235","actual_timestamp":"1484748840000","correction_ind":"false","event_source":"AUTOMATIC","train_file_address":"ATX","platform":" 2","division_code":"60","train_terminated":"false","train_id":"042K75MO18","offroute_ind":"false","variation_status":"LATE","train_service_code":"23587103","toc_id":"60","loc_stanox":"04235","auto_expected":"true","direction_ind":"DOWN","route":"0","planned_event_type":"ARRIVAL","next_report_stanox":"04221","line_ind":""}},{"header":{"msg_type":"0003","source_dev_id":"","user_id":"","original_data_source":"SMART","msg_queue_timestamp":"1484748849000","source_system_id":"TRUST"},"body":{"event_type":"DEPARTURE","gbtt_timestamp":"1484748720000","original_loc_stanox":"","planned_timestamp":"1484748720000","timetable_variation":"0","original_loc_timestamp":"","current_train_id":"","delay_monitoring_point":"false","next_report_run_time":"7","reporting_stanox":"00000","actual_timestamp":"1484748720000","correction_ind":"false","event_source":"AUTOMATIC","train_file_address":null,"platform":"","division_code":"23","train_terminated":"false","train_id":"301B23MM18","offroute_ind":"false","variation_status":"ON TIME","train_service_code":"21737000","toc_id":"23","loc_stanox":"29005","auto_expected":"true","direction_ind":"DOWN","route":"1","planned_event_type":"DEPARTURE","next_report_stanox":"29004","line_ind":""}},{"header":{"msg_type":"0003","source_dev_id":"","user_id":"","original_data_source":"SMART","msg_queue_timestamp":"1484748849000","source_system_id":"TRUST"},"body":{"event_type":"DEPARTURE","gbtt_timestamp":"1484748720000","original_loc_stanox":"","planned_timestamp":"1484748720000","timetable_variation":"0","original_loc_timestamp":"","current_train_id":"","delay_monitoring_point":"false","next_report_run_time":"2","reporting_stanox":"00000","actual_timestamp":"1484748720000","correction_ind":"false","event_source":"AUTOMATIC","train_file_address":null,"platform":"","division_code":"71","train_terminated":"false","train_id":"321D38MN18","offroute_ind":"false","variation_status":"ON TIME","train_service_code":"22345000","toc_id":"71","loc_stanox":"35321","auto_expected":"true","direction_ind":"DOWN","route":"3","planned_event_type":"DEPARTURE","next_report_stanox":"35325","line_ind":"E"}},{"header":{"msg_type":"0003","source_dev_id":"","user_id":"","original_data_source":"SMART","msg_queue_timestamp":"1484748849000","source_system_id":"TRUST"},"body":{"event_type":"ARRIVAL","gbtt_timestamp":"1484748900000","original_loc_stanox":"","planned_timestamp":"1484748870000","timetable_variation":"0","original_loc_timestamp":"","current_train_id":"","delay_monitoring_point":"true","next_report_run_time":"1","reporting_stanox":"35325","actual_timestamp":"1484748840000","correction_ind":"false","event_source":"AUTOMATIC","train_file_address":null,"platform":" 5","division_code":"71","train_terminated":"false","train_id":"321D38MN18","offroute_ind":"false","variation_status":"ON TIME","train_service_code":"22345000","toc_id":"71","loc_stanox":"35325","auto_expected":"true","direction_ind":"UP","route":"0","planned_event_type":"ARRIVAL","next_report_stanox":"35505","line_ind":""}},{"header":{"msg_type":"0003","source_dev_id":"","user_id":"","original_data_source":"SMART","msg_queue_timestamp":"1484748850000","source_system_id":"TRUST"},"body":{"event_type":"ARRIVAL","gbtt_timestamp":"1484748900000","original_loc_stanox":"","planned_timestamp":"1484748870000","timetable_variation":"0","original_loc_timestamp":"","current_train_id":"","delay_monitoring_point":"false","next_report_run_time":"1","reporting_stanox":"00000","actual_timestamp":"1484748840000","correction_ind":"false","event_source":"AUTOMATIC","train_file_address":null,"platform":" 1","division_code":"30","train_terminated":"false","train_id":"522Y69MO18","offroute_ind":"false","variation_status":"ON TIME","train_service_code":"22214000","toc_id":"30","loc_stanox":"52046","auto_expected":"true","direction_ind":"UP","route":"0","planned_event_type":"ARRIVAL","next_report_stanox":"52048","line_ind":""}},{"header":{"msg_type":"0003","source_dev_id":"","user_id":"","original_data_source":"SMART","msg_queue_timestamp":"1484748850000","source_system_id":"TRUST"},"body":{"event_type":"DEPARTURE","gbtt_timestamp":"1484748780000","original_loc_stanox":"","planned_timestamp":"1484748780000","timetable_variation":"1","original_loc_timestamp":"","current_train_id":"","delay_monitoring_point":"false","next_report_run_time":"2","reporting_stanox":"00000","actual_timestamp":"1484748840000","correction_ind":"false","event_source":"AUTOMATIC","train_file_address":null,"platform":"","division_code":"33","train_terminated":"false","train_id":"522W00MO18","offroute_ind":"false","variation_status":"LATE","train_service_code":"21381001","toc_id":"33","loc_stanox":"50431","auto_expected":"true","direction_ind":"DOWN","route":"2","planned_event_type":"DEPARTURE","next_report_stanox":"50423","line_ind":""}},{"header":{"msg_type":"0003","source_dev_id":"","user_id":"","original_data_source":"SMART","msg_queue_timestamp":"1484748850000","source_system_id":"TRUST"},"body":{"event_type":"DEPARTURE","gbtt_timestamp":"","original_loc_stanox":"","planned_timestamp":"1484748900000","timetable_variation":"2","original_loc_timestamp":"","current_train_id":"","delay_monitoring_point":"true","next_report_run_time":"4","reporting_stanox":"73822","actual_timestamp":"1484748780000","correction_ind":"false","event_source":"AUTOMATIC","train_file_address":null,"platform":" 3","division_code":"25","train_terminated":"false","train_id":"791L55MI18","offroute_ind":"false","variation_status":"EARLY","train_service_code":"25375002","toc_id":"25","loc_stanox":"73822","auto_expected":"true","direction_ind":"UP","route":"2","planned_event_type":"DEPARTURE","next_report_stanox":"73799","line_ind":"U"}},{"header":{"msg_type":"0003","source_dev_id":"","user_id":"","original_data_source":"SMART","msg_queue_timestamp":"1484748850000","source_system_id":"TRUST"},"body":{"event_type":"ARRIVAL","gbtt_timestamp":"1484748840000","original_loc_stanox":"","planned_timestamp":"1484748840000","timetable_variation":"0","original_loc_timestamp":"","current_train_id":"","delay_monitoring_point":"true","next_report_run_time":"1","reporting_stanox":"51203","actual_timestamp":"1484748840000","correction_ind":"false","event_source":"AUTOMATIC","train_file_address":null,"platform":" 1","division_code":"79","train_terminated":"false","train_id":"512D51MN18","offroute_ind":"false","variation_status":"ON TIME","train_service_code":"24936004","toc_id":"79","loc_stanox":"51203","auto_expected":"true","direction_ind":"UP","route":"0","planned_event_type":"ARRIVAL","next_report_stanox":"51311","line_ind":""}},{"header":{"msg_type":"0003","source_dev_id":"","user_id":"","original_data_source":"SMART","msg_queue_timestamp":"1484748851000","source_system_id":"TRUST"},"body":{"event_type":"ARRIVAL","gbtt_timestamp":"1484748900000","original_loc_stanox":"","planned_timestamp":"1484748900000","timetable_variation":"0","original_loc_timestamp":"","current_train_id":"","delay_monitoring_point":"false","next_report_run_time":"1","reporting_stanox":"00000","actual_timestamp":"1484748900000","correction_ind":"false","event_source":"AUTOMATIC","train_file_address":null,"platform":" 1","division_code":"84","train_terminated":"false","train_id":"872M40MO18","offroute_ind":"false","variation_status":"ON TIME","train_service_code":"24673405","toc_id":"84","loc_stanox":"87400","auto_expected":"true","direction_ind":"UP","route":"0","planned_event_type":"ARRIVAL","next_report_stanox":"87301","line_ind":""}},{"header":{"msg_type":"0003","source_dev_id":"","user_id":"","original_data_source":"SMART","msg_queue_timestamp":"1484748851000","source_system_id":"TRUST"},"body":{"event_type":"DEPARTURE","gbtt_timestamp":"1484748780000","original_loc_stanox":"","planned_timestamp":"1484748780000","timetable_variation":"0","original_loc_timestamp":"","current_train_id":"","delay_monitoring_point":"false","next_report_run_time":"2","reporting_stanox":"00000","actual_timestamp":"1484748780000","correction_ind":"false","event_source":"AUTOMATIC","train_file_address":null,"platform":" 1","division_code":"84","train_terminated":"false","train_id":"872M40MO18","offroute_ind":"false","variation_status":"ON TIME","train_service_code":"24673405","toc_id":"84","loc_stanox":"87403","auto_expected":"true","direction_ind":"UP","route":"1","planned_event_type":"DEPARTURE","next_report_stanox":"87400","line_ind":""}},{"header":{"msg_type":"0003","source_dev_id":"","user_id":"","original_data_source":"SMART","msg_queue_timestamp":"1484748851000","source_system_id":"TRUST"},"body":{"event_type":"DEPARTURE","gbtt_timestamp":"","original_loc_stanox":"","planned_timestamp":"1484748690000","timetable_variation":"2","original_loc_timestamp":"","current_train_id":"","delay_monitoring_point":"true","next_report_run_time":"3","reporting_stanox":"87249","actual_timestamp":"1484748780000","correction_ind":"false","event_source":"AUTOMATIC","train_file_address":null,"platform":" 1","division_code":"88","train_terminated":"false","train_id":"871W34MM18","offroute_ind":"false","variation_status":"LATE","train_service_code":"22721000","toc_id":"88","loc_stanox":"87249","auto_expected":"true","direction_ind":"UP","route":"4","planned_event_type":"DEPARTURE","next_report_stanox":"87247","line_ind":"L"}},{"header":{"msg_type":"0003","source_dev_id":"","user_id":"","original_data_source":"SMART","msg_queue_timestamp":"1484748851000","source_system_id":"TRUST"},"body":{"event_type":"ARRIVAL","gbtt_timestamp":"","original_loc_stanox":"","planned_timestamp":"1484751150000","timetable_variation":"38","original_loc_timestamp":"","current_train_id":null,"delay_monitoring_point":"false","next_report_run_time":"38","reporting_stanox":"00000","actual_timestamp":"1484748840000","correction_ind":"false","event_source":"AUTOMATIC","train_file_address":"ATW","platform":"","division_code":"00","train_terminated":"false","train_id":"23060BCM18","offroute_ind":"false","variation_status":"EARLY","train_service_code":"50520220","toc_id":"00","loc_stanox":"56524","auto_expected":"true","direction_ind":"","route":"0","planned_event_type":"ARRIVAL","next_report_stanox":"56550","line_ind":""}},{"header":{"msg_type":"0003","source_dev_id":"","user_id":"","original_data_source":"SMART","msg_queue_timestamp":"1484748851000","source_system_id":"TRUST"},"body":{"event_type":"DEPARTURE","gbtt_timestamp":"1484748600000","original_loc_stanox":"","planned_timestamp":"1484748600000","timetable_variation":"3","original_loc_timestamp":"","current_train_id":"","delay_monitoring_point":"true","next_report_run_time":"1","reporting_stanox":"69424","actual_timestamp":"1484748780000","correction_ind":"false","event_source":"AUTOMATIC","train_file_address":null,"platform":" 1","division_code":"74","train_terminated":"false","train_id":"631R33MM18","offroute_ind":"false","variation_status":"LATE","train_service_code":"25530004","toc_id":"74","loc_stanox":"69424","auto_expected":"true","direction_ind":"DOWN","route":"","planned_event_type":"DEPARTURE","next_report_stanox":"69438","line_ind":"2"}},{"header":{"msg_type":"0003","source_dev_id":"","user_id":"","original_data_source":"SMART","msg_queue_timestamp":"1484748851000","source_system_id":"TRUST"},"body":{"event_type":"ARRIVAL","gbtt_timestamp":"","original_loc_stanox":"","planned_timestamp":"1484748120000","timetable_variation":"13","original_loc_timestamp":"","current_train_id":"","delay_monitoring_point":"true","next_report_run_time":"1","reporting_stanox":"53401","actual_timestamp":"1484748900000","correction_ind":"false","event_source":"AUTOMATIC","train_file_address":null,"platform":"","division_code":"55","train_terminated":"false","train_id":"541H04MN18","offroute_ind":"false","variation_status":"LATE","train_service_code":"21750001","toc_id":"55","loc_stanox":"53401","auto_expected":"true","direction_ind":"","route":"0","planned_event_type":"ARRIVAL","next_report_stanox":"53231","line_ind":""}},{"header":{"msg_type":"0003","source_dev_id":"","user_id":"","original_data_source":"SMART","msg_queue_timestamp":"1484748851000","source_system_id":"TRUST"},"body":{"event_type":"ARRIVAL","gbtt_timestamp":"1484748900000","original_loc_stanox":"","planned_timestamp":"1484748900000","timetable_variation":"0","original_loc_timestamp":"","current_train_id":"","delay_monitoring_point":"false","next_report_run_time":"1","reporting_stanox":"00000","actual_timestamp":"1484748900000","correction_ind":"false","event_source":"AUTOMATIC","train_file_address":null,"platform":"","division_code":"29","train_terminated":"false","train_id":"361L78MM18","offroute_ind":"false","variation_status":"ON TIME","train_service_code":"22300000","toc_id":"29","loc_stanox":"65005","auto_expected":"true","direction_ind":"UP","route":"0","planned_event_type":"ARRIVAL","next_report_stanox":"65006","line_ind":""}},{"header":{"msg_type":"0003","source_dev_id":"","user_id":"","original_data_source":"SMART","msg_queue_timestamp":"1484748851000","source_system_id":"TRUST"},"body":{"event_type":"ARRIVAL","gbtt_timestamp":"1484748900000","original_loc_stanox":"","planned_timestamp":"1484748870000","timetable_variation":"0","original_loc_timestamp":"","current_train_id":"","delay_monitoring_point":"true","next_report_run_time":"1","reporting_stanox":"52736","actual_timestamp":"1484748840000","correction_ind":"false","event_source":"AUTOMATIC","train_file_address":null,"platform":" 3","division_code":"30","train_terminated":"false","train_id":"512U47MN18","offroute_ind":"false","variation_status":"ON TIME","train_service_code":"21234001","toc_id":"30","loc_stanox":"52736","auto_expected":"true","direction_ind":"UP","route":"0","planned_event_type":"ARRIVAL","next_report_stanox":"52737","line_ind":""}},{"header":{"msg_type":"0003","source_dev_id":"","user_id":"","original_data_source":"SMART","msg_queue_timestamp":"1484748851000","source_system_id":"TRUST"},"body":{"event_type":"ARRIVAL","gbtt_timestamp":"1484748900000","original_loc_stanox":"","planned_timestamp":"1484748900000","timetable_variation":"0","original_loc_timestamp":"","current_train_id":"","delay_monitoring_point":"true","next_report_run_time":"2","reporting_stanox":"74436","actual_timestamp":"1484748900000","correction_ind":"false","event_source":"AUTOMATIC","train_file_address":null,"platform":" 2","division_code":"74","train_terminated":"false","train_id":"741Y47MO18","offroute_ind":"false","variation_status":"ON TIME","train_service_code":"25535004","toc_id":"74","loc_stanox":"74436","auto_expected":"true","direction_ind":"DOWN","route":"0","planned_event_type":"ARRIVAL","next_report_stanox":"74557","line_ind":""}},{"header":{"msg_type":"0003","source_dev_id":"","user_id":"","original_data_source":"SMART","msg_queue_timestamp":"1484748851000","source_system_id":"TRUST"},"body":{"event_type":"DEPARTURE","gbtt_timestamp":"1484748780000","original_loc_stanox":"","planned_timestamp":"1484748780000","timetable_variation":"0","original_loc_timestamp":"","current_train_id":"","delay_monitoring_point":"true","next_report_run_time":"3","reporting_stanox":"74446","actual_timestamp":"1484748780000","correction_ind":"false","event_source":"AUTOMATIC","train_file_address":null,"platform":" 4","division_code":"27","train_terminated":"false","train_id":"741E48MN18","offroute_ind":"false","variation_status":"ON TIME","train_service_code":"22180011","toc_id":"27","loc_stanox":"74446","auto_expected":"true","direction_ind":"DOWN","route":"1","planned_event_type":"DEPARTURE","next_report_stanox":"74449","line_ind":"M"}},{"header":{"msg_type":"0003","source_dev_id":"","user_id":"","original_data_source":"SMART","msg_queue_timestamp":"1484748851000","source_system_id":"TRUST"},"body":{"event_type":"DEPARTURE","gbtt_timestamp":"1484748780000","original_loc_stanox":"","planned_timestamp":"1484748780000","timetable_variation":"1","original_loc_timestamp":"","current_train_id":"","delay_monitoring_point":"false","next_report_run_time":"3","reporting_stanox":"00000","actual_timestamp":"1484748720000","correction_ind":"false","event_source":"AUTOMATIC","train_file_address":null,"platform":"","division_code":"71","train_terminated":"false","train_id":"772T30MO18","offroute_ind":"false","variation_status":"EARLY","train_service_code":"25447000","toc_id":"71","loc_stanox":"78420","auto_expected":"true","direction_ind":"UP","route":"1","planned_event_type":"DEPARTURE","next_report_stanox":"78410","line_ind":""}},{"header":{"msg_type":"0003","source_dev_id":"","user_id":"","original_data_source":"SMART","msg_queue_timestamp":"1484748851000","source_system_id":"TRUST"},"body":{"event_type":"DEPARTURE","gbtt_timestamp":"1484748780000","original_loc_stanox":"","planned_timestamp":"1484748780000","timetable_variation":"0","original_loc_timestamp":"","current_train_id":"","delay_monitoring_point":"true","next_report_run_time":"3","reporting_stanox":"81501","actual_timestamp":"1484748780000","correction_ind":"false","event_source":"AUTOMATIC","train_file_address":null,"platform":" 2","division_code":"25","train_terminated":"false","train_id":"811A20MO18","offroute_ind":"false","variation_status":"ON TIME","train_service_code":"25370002","toc_id":"25","loc_stanox":"81501","auto_expected":"true","direction_ind":"UP","route":"2","planned_event_type":"DEPARTURE","next_report_stanox":"75356","line_ind":""}},{"header":{"msg_type":"0003","source_dev_id":"","user_id":"","original_data_source":"SMART","msg_queue_timestamp":"1484748851000","source_system_id":"TRUST"},"body":{"event_type":"ARRIVAL","gbtt_timestamp":"1484748960000","original_loc_stanox":"","planned_timestamp":"1484748930000","timetable_variation":"0","original_loc_timestamp":"","current_train_id":"","delay_monitoring_point":"true","next_report_run_time":"1","reporting_stanox":"87069","actual_timestamp":"1484748900000","correction_ind":"false","event_source":"AUTOMATIC","train_file_address":null,"platform":"","division_code":"84","train_terminated":"false","train_id":"872G42MO18","offroute_ind":"false","variation_status":"ON TIME","train_service_code":"24673505","toc_id":"84","loc_stanox":"87069","auto_expected":"true","direction_ind":"UP","route":"0","planned_event_type":"ARRIVAL","next_report_stanox":"87070","line_ind":""}},{"header":{"msg_type":"0003","source_dev_id":"","user_id":"","original_data_source":"SMART","msg_queue_timestamp":"1484748851000","source_system_id":"TRUST"},"body":{"event_type":"ARRIVAL","gbtt_timestamp":"1484748900000","original_loc_stanox":"","planned_timestamp":"1484748870000","timetable_variation":"0","original_loc_timestamp":"","current_train_id":"","delay_monitoring_point":"true","next_report_run_time":"1","reporting_stanox":"87071","actual_timestamp":"1484748840000","correction_ind":"false","event_source":"AUTOMATIC","train_file_address":null,"platform":" 2","division_code":"84","train_terminated":"false","train_id":"872G35MN18","offroute_ind":"false","variation_status":"ON TIME","train_service_code":"24673505","toc_id":"84","loc_stanox":"87071","auto_expected":"true","direction_ind":"DOWN","route":"0","planned_event_type":"ARRIVAL","next_report_stanox":"87070","line_ind":""}},{"header":{"msg_type":"0003","source_dev_id":"","user_id":"","original_data_source":"SMART","msg_queue_timestamp":"1484748851000","source_system_id":"TRUST"},"body":{"event_type":"ARRIVAL","gbtt_timestamp":"1484748840000","original_loc_stanox":"","planned_timestamp":"1484748840000","timetable_variation":"0","original_loc_timestamp":"","current_train_id":"","delay_monitoring_point":"true","next_report_run_time":"1","reporting_stanox":"86341","actual_timestamp":"1484748840000","correction_ind":"false","event_source":"AUTOMATIC","train_file_address":null,"platform":" 2","division_code":"84","train_terminated":"false","train_id":"871P37MM18","offroute_ind":"false","variation_status":"ON TIME","train_service_code":"24621104","toc_id":"84","loc_stanox":"86341","auto_expected":"true","direction_ind":"DOWN","route":"0","planned_event_type":"ARRIVAL","next_report_stanox":"86334","line_ind":""}},{"header":{"msg_type":"0003","source_dev_id":"","user_id":"","original_data_source":"SMART","msg_queue_timestamp":"1484748851000","source_system_id":"TRUST"},"body":{"event_type":"DEPARTURE","gbtt_timestamp":"1484748780000","original_loc_stanox":"","planned_timestamp":"1484748810000","timetable_variation":"1","original_loc_timestamp":"","current_train_id":"","delay_monitoring_point":"true","next_report_run_time":"5","reporting_stanox":"48013","actual_timestamp":"1484748840000","correction_ind":"false","event_source":"AUTOMATIC","train_file_address":null,"platform":"","division_code":"21","train_terminated":"false","train_id":"482S17MN18","offroute_ind":"false","variation_status":"LATE","train_service_code":"21897002","toc_id":"21","loc_stanox":"48013","auto_expected":"true","direction_ind":"UP","route":"2","planned_event_type":"DEPARTURE","next_report_stanox":"48016","line_ind":""}},{"header":{"msg_type":"0003","source_dev_id":"VDJG","user_id":"#QLP1003","original_data_source":"SDR","msg_queue_timestamp":"1484748851000","source_system_id":"TRUST"},"body":{"event_type":"ARRIVAL","gbtt_timestamp":"1484748780000","original_loc_stanox":"","planned_timestamp":"1484748750000","timetable_variation":"0","original_loc_timestamp":"","current_train_id":"","delay_monitoring_point":"false","next_report_run_time":"1","reporting_stanox":"00000","actual_timestamp":"1484748720000","correction_ind":"false","event_source":"MANUAL","train_file_address":null,"platform":"","division_code":"60","train_terminated":"false","train_id":"071E76MK18","offroute_ind":"false","variation_status":"ON TIME","train_service_code":"23579003","toc_id":"60","loc_stanox":"09033","auto_expected":"","direction_ind":"","route":"0","planned_event_type":"ARRIVAL","next_report_stanox":"09085","line_ind":""}},{"header":{"msg_type":"0003","source_dev_id":"VDJG","user_id":"#QLP1003","original_data_source":"SDR","msg_queue_timestamp":"1484748851000","source_system_id":"TRUST"},"body":{"event_type":"DEPARTURE","gbtt_timestamp":"1484748780000","original_loc_stanox":"","planned_timestamp":"1484748780000","timetable_variation":"0","original_loc_timestamp":"","current_train_id":"","delay_monitoring_point":"false","next_report_run_time":"8","reporting_stanox":"00000","actual_timestamp":"1484748780000","correction_ind":"false","event_source":"MANUAL","train_file_address":null,"platform":"","division_code":"60","train_terminated":"false","train_id":"071E76MK18","offroute_ind":"false","variation_status":"ON TIME","train_service_code":"23579003","toc_id":"60","loc_stanox":"09033","auto_expected":"","direction_ind":"","route":"","planned_event_type":"DEPARTURE","next_report_stanox":"09085","line_ind":""}}]